odoo/addons/stock_barcodes_move_location/README.rst
odoo/addons/stock_barcodes_move_location/__init__.py
odoo/addons/stock_barcodes_move_location/__manifest__.py
odoo/addons/stock_barcodes_move_location/i18n/stock_barcodes_move_location.pot
odoo/addons/stock_barcodes_move_location/models/__init__.py
odoo/addons/stock_barcodes_move_location/models/stock_picking_type.py
odoo/addons/stock_barcodes_move_location/static/description/icon.png
odoo/addons/stock_barcodes_move_location/static/description/index.html
odoo/addons/stock_barcodes_move_location/static/src/img/scan.png
odoo/addons/stock_barcodes_move_location/static/src/js/stock_barcodes.js
odoo/addons/stock_barcodes_move_location/views/assets.xml
odoo/addons/stock_barcodes_move_location/views/stock_picking_type_views.xml
odoo/addons/stock_barcodes_move_location/wizard/__init__.py
odoo/addons/stock_barcodes_move_location/wizard/stock_barcodes_read_move_location.py
odoo/addons/stock_barcodes_move_location/wizard/stock_barcodes_read_move_location_views.xml
odoo/addons/stock_barcodes_move_location/wizard/stock_move_location.py
odoo/addons/stock_barcodes_move_location/wizard/stock_move_location_views.xml
odoo13_addon_stock_barcodes_move_location-13.0.1.0.1.dist-info/METADATA
odoo13_addon_stock_barcodes_move_location-13.0.1.0.1.dist-info/WHEEL
odoo13_addon_stock_barcodes_move_location-13.0.1.0.1.dist-info/top_level.txt
odoo13_addon_stock_barcodes_move_location-13.0.1.0.1.dist-info/RECORD
