Metadata-Version: 2.1
Name: odoo13-addon-stock-barcodes-move-location
Version: 13.0.1.0.1
Summary: It provides read barcode on stock operations.
Home-page: https://odoo-community.org/
Author: Tecnativa, Odoo Community Association (OCA)
Author-email: support@odoo-community.org
License: AGPL-3
Platform: UNKNOWN
Classifier: Programming Language :: Python
Classifier: Framework :: Odoo
Classifier: License :: OSI Approved :: GNU Affero General Public License v3
Requires-Python: >=3.5
Requires-Dist: odoo13-addon-stock-barcodes
Requires-Dist: odoo13-addon-stock-barcodes-automatic-entry
Requires-Dist: odoo13-addon-stock-move-location
Requires-Dist: odoo (<13.1dev,>=13.0a)
